c_explainer.cpython-311-aarch64-linux-gnu.so
pyxai/version.txt
pyxai/__init__.py
pyxai/Learning.py
pyxai/Builder.py
pyxai/Tools.py
pyxai/convert.py
pyxai/Explainer.py
pyxai/setup.py
pyxai/explanations/BT_wine_regression.explainer
pyxai/explanations/RF_buba.explainer
pyxai/explanations/BT_builder_simple.explainer
pyxai/explanations/RF_cifar_cat_minimal_majoritary.explainer
pyxai/explanations/BT_builder_regression.explainer
pyxai/explanations/DT_mnist38_hot_map.explainer
pyxai/explanations/RF_australian_theory.explainer
pyxai/explanations/BT_iris.explainer
pyxai/explanations/RF_mnist49_minimal_majoritary.explainer
pyxai/explanations/DT_mnist38_contrastives.explainer
pyxai/explanations/RF_breast_tumor_theory.explainer
pyxai/explanations/DT_orchid.explainer
pyxai/explanations/DT_wine.explainer
pyxai/explanations/RF_iris_majoritary_theory.explainer
pyxai/explanations/RF_biodegradation.explainer
pyxai/explanations/BT_mnist38_tree_specific_class_3.explainer
pyxai/explanations/RF_australian_majoritary.explainer
pyxai/explanations/RF_cnae.explainer
pyxai/explanations/BT_mnist38_tree_specific_class_8.explainer
pyxai/explanations/DT_dexter.explainer
pyxai/explanations/DT_loan.explainer
pyxai/examples/RF/GUI-australian.py
pyxai/examples/RF/builder-categorical.py
pyxai/examples/RF/builder-cattleya.py
pyxai/examples/RF/builder-loan-simple.py
pyxai/examples/RF/simple.py
pyxai/examples/RF/theories-types-file.py
pyxai/examples/RF/builder-multiclasses.py
pyxai/examples/RF/builder-categorical-paper.py
pyxai/examples/RF/theories-types-dict.py
pyxai/examples/RF/theories-majoritary.py
pyxai/examples/RF/GUI-mnist49.py
pyxai/examples/RF/GUI-builder-loan.py
pyxai/examples/RF/builder-loan.py
pyxai/examples/Converters/converter-cleveland.py
pyxai/examples/Converters/converter-balance-scale.py
pyxai/examples/Converters/converter-adult.py
pyxai/examples/Converters/converter-cifar.py
pyxai/examples/Converters/converter-regression.py
pyxai_experimental-1.1.2.dist-info/LICENSE
pyxai_experimental-1.1.2.dist-info/RECORD
pyxai_experimental-1.1.2.dist-info/WHEEL
pyxai_experimental-1.1.2.dist-info/METADATA
pyxai_experimental-1.1.2.dist-info/top_level.txt
