Metadata-Version: 2.1
Name: pyxai-experimental
Version: 1.1.2
Summary: Explaining Machine Learning Classifiers in Python
Home-page: UNKNOWN
Author: Gilles Audemard, Steve Bellart, Louenas Bounia, Jean-Marie Lagniez, Pierre Marquis, Nicolas Szczepanski:
Author-email: audemard@cril.fr, bellart@cril.fr, bounia@cril.fr, lagniez@cril.fr, marquis@cril.fr, szczepanski@cril.fr
Maintainer: Gilles Audemard, Nicolas Szczepanski
Maintainer-email: audemard@cril.fr, szczepanski@cril.fr
License: MIT
Project-URL: Documentation, http://www.cril.univ-artois.fr/pyxai/
Project-URL: Installation, http://www.cril.univ-artois.fr/pyxai/documentation/installation/
Project-URL: Git, https://github.com/crillab/pyxai
Keywords: XAI AI XML ML explainable learning
Platform: LINUX
Classifier: Topic :: Scientific/Engineering :: Artificial Intelligence
Classifier: Topic :: Education
Requires-Python: >=3.6
License-File: LICENSE
Requires-Dist: lxml
Requires-Dist: numpy
Requires-Dist: wheel
Requires-Dist: pandas
Requires-Dist: termcolor
Requires-Dist: shap
Requires-Dist: wordfreq
Requires-Dist: python-sat[aiger,pblib]
Requires-Dist: xgboost
Requires-Dist: pycsp3
Requires-Dist: matplotlib
Requires-Dist: pyqt6
Requires-Dist: dill
Requires-Dist: lightgbm
Requires-Dist: docplex
